pyapril/RDTools.py
pyapril/__init__.py
pyapril/caCfar.py
pyapril/channelPreparation.py
pyapril/clutterCancellation.py
pyapril/detector.py
pyapril/hitProcessor.py
pyapril/metricExtract.py
pyapril/targetLocalization.py
pyapril/targetParamCalculator.py
pyapril/sim/FMSimulator.py
pyapril/sim/__init__.py
pyapril/tools/__init__.py
pyapril/tools/resample.py
pyAPRiL-1.7.6.dist-info/LICENSE
pyAPRiL-1.7.6.dist-info/METADATA
pyAPRiL-1.7.6.dist-info/WHEEL
pyAPRiL-1.7.6.dist-info/top_level.txt
pyAPRiL-1.7.6.dist-info/RECORD
