Metadata-Version: 2.1
Name: pyAPRiL
Version: 1.7.6
Summary: A python based passive radar library
Home-page: https://github.com/petotamas/APRiL
Author: Tamas Peto
Author-email: petotax@gmail.com
License: UNKNOWN
Platform: UNKNOWN
Classifier: Programming Language :: Python :: 3
Classifier: License :: OSI Approved :: GNU General Public License v3 (GPLv3)  
Classifier: Operating System :: OS Independent
Classifier: Topic :: Scientific/Engineering
